mt_thresholds.py
mt_thresholds-1.0.4.dist-info/METADATA
mt_thresholds-1.0.4.dist-info/WHEEL
mt_thresholds-1.0.4.dist-info/entry_points.txt
mt_thresholds-1.0.4.dist-info/top_level.txt
mt_thresholds-1.0.4.dist-info/RECORD
