Metadata-Version: 2.2
Name: mt-thresholds
Version: 1.0.4
Summary: Tool to check how metric deltas for machine translation reflect on system-level human accuracies.
Author-email: Tom Kocmi <tomkocmi@microsoft.com>, Vilém Zouhar <vzouhar@ethz.ch>
Project-URL: Homepage, https://github.com/kocmitom/MT-Thresholds
Project-URL: Issues, https://github.com/kocmitom/MT-Thresholds/issues
Project-URL: Demo, https://kocmitom.github.io/MT-Thresholds
Keywords: machine-translation,evaluation
Requires-Python: >=3.10
